py_nymta-0.3.3.dist-info/licenses/LICENSE
pymta/__init__.py
pymta/constants.py
pymta/gtfs_static.py
pymta/models.py
pymta/py.typed
py_nymta-0.3.3.dist-info/METADATA
py_nymta-0.3.3.dist-info/WHEEL
py_nymta-0.3.3.dist-info/top_level.txt
py_nymta-0.3.3.dist-info/RECORD
