Metadata-Version: 2.4
Name: py-nymta
Version: 0.3.3
Summary: Python library for accessing MTA (Metropolitan Transportation Authority) real-time transit data for NYC
Author: py-nymta Contributors
License: MIT
Project-URL: Homepage, https://github.com/OnFreund/py-nymta
Project-URL: Issues, https://github.com/OnFreund/py-nymta/issues
Classifier: Development Status :: 3 - Alpha
Classifier: Intended Audience :: Developers
Classifier: License :: OSI Approved :: MIT License
Classifier: Programming Language :: Python :: 3
Classifier: Programming Language :: Python :: 3.11
Classifier: Programming Language :: Python :: 3.12
Classifier: Programming Language :: Python :: 3.13
Requires-Python: >=3.11
License-File: LICENSE
Requires-Dist: gtfs-realtime-bindings>=2.0.0
Requires-Dist: aiohttp>=3.9.0
Requires-Dist: aiofiles>=23.0.0
Dynamic: license-file
